{"meta":{"per_page":23,"total":21,"geolocation":null,"took":8,"page":1},"events":[{"links":[],"id":1806680,"stats":{"listing_count":3,"average_price":57.0,"lowest_price":56.0,"highest_price":107.0},"title":"Dr. Dog","announce_date":"2013-09-24T17:41:52","score":0.49236,"date_tbd":false,"type":"concert","datetime_local":"2014-02-22T21:00:00","visible_until_utc":"2014-02-23T07:00:00","time_tbd":false,"taxonomies":[{"parent_id":null,"id":2000000,"name":"concert"}],"performers":[{"name":"Dr. Dog","short_name":"Dr. Dog","url":"http://seatgeek.com/dr-dog-tickets","type":"band","image":"http://cdn.chairnerd.com/images/performers-landscape/dr-dog-5d6144/640/huge.jpg","primary":true,"home_venue_id":null,"slug":"dr-dog","score":0.52272,"images":{"huge":"http://cdn.chairnerd.com/images/performers-landscape/dr-dog-5d6144/640/huge.jpg","medium":"http://cdn.chairnerd.com/images/performers/640/dr-dog-f8a49b/medium.jpg","large":"http://cdn.chairnerd.com/images/performers/640/dr-dog-b47029/large.jpg","small":"http://cdn.chairnerd.com/images/performers/640/dr-dog-a0a3c9/small.jpg"},"id":640}],"url":"http://seatgeek.com/dr-dog-tickets/dallas-texas-house-of-blues-dallas-2014-02-22-9-pm/concert/1806680/","created_at":"2013-09-24T17:41:52","venue":{"city":"Dallas","name":"House of Blues Dallas","extended_address":"Dallas, TX 75202","url":"http://seatgeek.com/venues/house-of-blues-dallas/tickets/","country":"US","display_location":"Dallas, TX","links":[],"slug":"house-of-blues-dallas","state":"TX","score":0.56368,"postal_code":"75202","location":{"lat":32.813,"lon":-96.7698},"address":"2200 N. Lamar Street","timezone":"America/Chicago","id":564},"short_title":"Dr. Dog","datetime_utc":"2014-02-23T03:00:00","datetime_tbd":false},{"links":[],"id":1807066,"stats":{"listing_count":7,"average_price":93,"lowest_price":84,"highest_price":104},"title":"Dr. Dog with Saint Rich","announce_date":"2013-09-24T17:42:40","score":0.46226,"date_tbd":false,"type":"concert","datetime_local":"2014-02-24T20:30:00","visible_until_utc":"2014-02-25T07:30:00","time_tbd":false,"taxonomies":[{"parent_id":null,"id":2000000,"name":"concert"}],"performers":[{"name":"Dr. Dog","short_name":"Dr. Dog","url":"http://seatgeek.com/dr-dog-tickets","type":"band","image":"http://cdn.chairnerd.com/images/performers-landscape/dr-dog-5d6144/640/huge.jpg","primary":true,"home_venue_id":null,"slug":"dr-dog","score":0.52272,"images":{"huge":"http://cdn.chairnerd.com/images/performers-landscape/dr-dog-5d6144/640/huge.jpg","medium":"http://cdn.chairnerd.com/images/performers/640/dr-dog-f8a49b/medium.jpg","large":"http://cdn.chairnerd.com/images/performers/640/dr-dog-b47029/large.jpg","small":"http://cdn.chairnerd.com/images/performers/640/dr-dog-a0a3c9/small.jpg"},"id":640},{"name":"Saint Rich","short_name":"Saint Rich","url":"http://seatgeek.com/saint-rich-tickets","type":"band","image":null,"home_venue_id":null,"slug":"saint-rich","score":0.42852,"images":{},"id":252348}],"url":"http://seatgeek.com/dr-dog-with-saint-rich-tickets/phoenix-arizona-crescent-ballroom-2014-02-24-8-30-pm/concert/1807066/","created_at":"2013-09-24T17:42:40","venue":{"city":"Phoenix","name":"Crescent Ballroom","extended_address":"Phoenix, AZ 85003","url":"http://seatgeek.com/venues/crescent-ballroom/tickets/","country":"US","display_location":"Phoenix, AZ","links":[],"slug":"crescent-ballroom","state":"AZ","score":0.48401,"postal_code":"85003","location":{"lat":33.45,"lon":-112.08},"address":"308 N. 2nd Ave.","timezone":"America/Phoenix","id":7698},"short_title":"Dr. Dog with Saint Rich","datetime_utc":"2014-02-25T03:30:00","general_admission":true,"datetime_tbd":false},{"links":[],"id":1807067,"stats":{"listing_count":8,"average_price":77.5,"lowest_price":70.0,"highest_price":86.0},"title":"Dr. Dog with Saint Rich","announce_date":"2013-09-24T17:42:40","score":0.4898,"date_tbd":false,"type":"concert","datetime_local":"2014-02-25T20:30:00","visible_until_utc":"2014-02-26T07:30:00","time_tbd":false,"taxonomies":[{"parent_id":null,"id":2000000,"name":"concert"}],"performers":[{"name":"Dr. Dog","short_name":"Dr. Dog","url":"http://seatgeek.com/dr-dog-tickets","type":"band","image":"http://cdn.chairnerd.com/images/performers-landscape/dr-dog-5d6144/640/huge.jpg","primary":true,"home_venue_id":null,"slug":"dr-dog","score":0.52272,"images":{"huge":"http://cdn.chairnerd.com/images/performers-landscape/dr-dog-5d6144/640/huge.jpg","medium":"http://cdn.chairnerd.com/images/performers/640/dr-dog-f8a49b/medium.jpg","large":"http://cdn.chairnerd.com/images/performers/640/dr-dog-b47029/large.jpg","small":"http://cdn.chairnerd.com/images/performers/640/dr-dog-a0a3c9/small.jpg"},"id":640},{"name":"Saint Rich","short_name":"Saint Rich","url":"http://seatgeek.com/saint-rich-tickets","type":"band","image":null,"home_venue_id":null,"slug":"saint-rich","score":0.42852,"images":{},"id":252348}],"url":"http://seatgeek.com/dr-dog-with-saint-rich-tickets/phoenix-arizona-crescent-ballroom-2014-02-25-8-30-pm/concert/1807067/","created_at":"2013-09-24T17:42:40","venue":{"city":"Phoenix","name":"Crescent Ballroom","extended_address":"Phoenix, AZ 85003","url":"http://seatgeek.com/venues/crescent-ballroom/tickets/","country":"US","display_location":"Phoenix, AZ","links":[],"slug":"crescent-ballroom","state":"AZ","score":0.48401,"postal_code":"85003","location":{"lat":33.45,"lon":-112.08},"address":"308 N. 2nd Ave.","timezone":"America/Phoenix","id":7698},"short_title":"Dr. Dog with Saint Rich","datetime_utc":"2014-02-26T03:30:00","general_admission":true,"datetime_tbd":false},{"links":[],"id":1806761,"stats":{"listing_count":22,"average_price":64.5,"lowest_price":55,"highest_price":166},"title":"Dr. Dog","announce_date":"2013-09-24T17:42:00","score":0.48611,"date_tbd":false,"type":"concert","datetime_local":"2014-02-26T20:00:00","visible_until_utc":"2014-02-27T08:00:00","time_tbd":false,"taxonomies":[{"parent_id":null,"id":2000000,"name":"concert"}],"performers":[{"name":"Dr. Dog","short_name":"Dr. Dog","url":"http://seatgeek.com/dr-dog-tickets","type":"band","image":"http://cdn.chairnerd.com/images/performers-landscape/dr-dog-5d6144/640/huge.jpg","primary":true,"home_venue_id":null,"slug":"dr-dog","score":0.52272,"images":{"huge":"http://cdn.chairnerd.com/images/performers-landscape/dr-dog-5d6144/640/huge.jpg","medium":"http://cdn.chairnerd.com/images/performers/640/dr-dog-f8a49b/medium.jpg","large":"http://cdn.chairnerd.com/images/performers/640/dr-dog-b47029/large.jpg","small":"http://cdn.chairnerd.com/images/performers/640/dr-dog-a0a3c9/small.jpg"},"id":640}],"url":"http://seatgeek.com/dr-dog-tickets/santa-ana-california-the-observatory-1-2014-02-26-8-pm/concert/1806761/","created_at":"2013-09-24T17:42:00","venue":{"city":"Santa Ana","name":"The Observatory","extended_address":"Santa Ana, CA 92704","url":"http://seatgeek.com/venues/the-observatory-1/tickets/","country":"US","display_location":"Santa Ana, CA","links":[],"slug":"the-observatory-1","state":"CA","score":0.50204,"postal_code":"92704","location":{"lat":33.7005,"lon":-117.919},"address":"3503 S. Harbor Blvd.","timezone":"America/Los_Angeles","id":1899},"short_title":"Dr. Dog","datetime_utc":"2014-02-27T04:00:00","general_admission":true,"datetime_tbd":false},{"links":[],"id":1814112,"stats":{"listing_count":57,"average_price":62.0,"lowest_price":46.0,"highest_price":82.0},"title":"Dr. Dog with Saint Rich","announce_date":"2013-10-01T17:22:02","score":0.53221,"date_tbd":false,"type":"concert","datetime_local":"2014-02-27T20:00:00","visible_until_utc":"2014-02-28T08:00:00","time_tbd":false,"taxonomies":[{"parent_id":null,"id":2000000,"name":"concert"}],"performers":[{"name":"Dr. Dog","short_name":"Dr. Dog","url":"http://seatgeek.com/dr-dog-tickets","type":"band","image":"http://cdn.chairnerd.com/images/performers-landscape/dr-dog-5d6144/640/huge.jpg","primary":true,"home_venue_id":null,"slug":"dr-dog","score":0.52272,"images":{"huge":"http://cdn.chairnerd.com/images/performers-landscape/dr-dog-5d6144/640/huge.jpg","medium":"http://cdn.chairnerd.com/images/performers/640/dr-dog-f8a49b/medium.jpg","large":"http://cdn.chairnerd.com/images/performers/640/dr-dog-b47029/large.jpg","small":"http://cdn.chairnerd.com/images/performers/640/dr-dog-a0a3c9/small.jpg"},"id":640},{"name":"Saint Rich","short_name":"Saint Rich","url":"http://seatgeek.com/saint-rich-tickets","type":"band","image":null,"home_venue_id":null,"slug":"saint-rich","score":0.42852,"images":{},"id":252348}],"url":"http://seatgeek.com/dr-dog-with-saint-rich-tickets/los-angeles-california-the-wiltern-1-2014-02-27-8-pm/concert/1814112/","created_at":"2013-10-01T17:22:02","venue":{"city":"Los Angeles","name":"The Wiltern","extended_address":"Los Angeles, CA 90010","url":"http://seatgeek.com/venues/the-wiltern-1/tickets/","country":"US","display_location":"Los Angeles, CA","links":[],"slug":"the-wiltern-1","state":"CA","score":0.64558,"postal_code":"90010","location":{"lat":34.0617,"lon":-118.309},"address":"3790 Wilshire Blvd.","timezone":"America/Los_Angeles","id":456},"short_title":"Dr. Dog with Saint Rich","datetime_utc":"2014-02-28T04:00:00","datetime_tbd":false},{"links":[],"id":1806934,"stats":{"listing_count":10,"average_price":61.5,"lowest_price":44.0,"highest_price":193.0},"title":"Dr. Dog with Saint Rich","announce_date":"2013-09-24T17:42:27","score":0.47033,"date_tbd":false,"type":"concert","datetime_local":"2014-02-28T19:00:00","visible_until_utc":"2014-03-01T07:00:00","time_tbd":false,"taxonomies":[{"parent_id":null,"id":2000000,"name":"concert"}],"performers":[{"name":"Dr. Dog","short_name":"Dr. Dog","url":"http://seatgeek.com/dr-dog-tickets","type":"band","image":"http://cdn.chairnerd.com/images/performers-landscape/dr-dog-5d6144/640/huge.jpg","primary":true,"home_venue_id":null,"slug":"dr-dog","score":0.52272,"images":{"huge":"http://cdn.chairnerd.com/images/performers-landscape/dr-dog-5d6144/640/huge.jpg","medium":"http://cdn.chairnerd.com/images/performers/640/dr-dog-f8a49b/medium.jpg","large":"http://cdn.chairnerd.com/images/performers/640/dr-dog-b47029/large.jpg","small":"http://cdn.chairnerd.com/images/performers/640/dr-dog-a0a3c9/small.jpg"},"id":640},{"name":"Saint Rich","short_name":"Saint Rich","url":"http://seatgeek.com/saint-rich-tickets","type":"band","image":null,"home_venue_id":null,"slug":"saint-rich","score":0.42852,"images":{},"id":252348}],"url":"http://seatgeek.com/dr-dog-with-saint-rich-tickets/santa-cruz-california-the-catalyst-2014-02-28-7-pm/concert/1806934/","created_at":"2013-09-24T17:42:27","venue":{"city":"Santa Cruz","name":"The Catalyst","extended_address":"Santa Cruz, CA 95060","url":"http://seatgeek.com/venues/the-catalyst/tickets/","country":"US","display_location":"Santa Cruz, CA","links":[],"slug":"the-catalyst","state":"CA","score":0.50872,"postal_code":"95060","location":{"lat":36.9714,"lon":-122.025},"address":"1011 Pacific Avenue","timezone":"America/Los_Angeles","id":890},"short_title":"Dr. Dog with Saint Rich","datetime_utc":"2014-03-01T03:00:00","general_admission":true,"datetime_tbd":false},{"links":[],"id":1809698,"stats":{"listing_count":3,"average_price":54,"lowest_price":54,"highest_price":55},"title":"Dr. Dog","announce_date":"2013-09-26T17:37:29","score":0.48156,"date_tbd":false,"type":"concert","datetime_local":"2014-03-03T19:00:00","visible_until_utc":"2014-03-04T07:00:00","time_tbd":false,"taxonomies":[{"parent_id":null,"id":2000000,"name":"concert"}],"performers":[{"name":"Dr. Dog","short_name":"Dr. Dog","url":"http://seatgeek.com/dr-dog-tickets","type":"band","image":"http://cdn.chairnerd.com/images/performers-landscape/dr-dog-5d6144/640/huge.jpg","primary":true,"home_venue_id":null,"slug":"dr-dog","score":0.52272,"images":{"huge":"http://cdn.chairnerd.com/images/performers-landscape/dr-dog-5d6144/640/huge.jpg","medium":"http://cdn.chairnerd.com/images/performers/640/dr-dog-f8a49b/medium.jpg","large":"http://cdn.chairnerd.com/images/performers/640/dr-dog-b47029/large.jpg","small":"http://cdn.chairnerd.com/images/performers/640/dr-dog-a0a3c9/small.jpg"},"id":640}],"url":"http://seatgeek.com/dr-dog-tickets/portland-oregon-crystal-ballroom-1-2014-03-03-7-pm/concert/1809698/","created_at":"2013-09-26T17:37:29","venue":{"city":"Portland","name":"Crystal Ballroom","extended_address":"Portland, OR 97209","url":"http://seatgeek.com/venues/crystal-ballroom-1/tickets/","country":"US","display_location":"Portland, OR","links":[],"slug":"crystal-ballroom-1","state":"OR","score":0.54237,"postal_code":"97209","location":{"lat":45.5229,"lon":-122.685},"address":"1332 W. Burnside","timezone":"America/Los_Angeles","id":756},"short_title":"Dr. Dog","datetime_utc":"2014-03-04T03:00:00","general_admission":true,"datetime_tbd":false},{"links":[],"id":1806845,"stats":{"listing_count":8,"average_price":79.0,"lowest_price":47.0,"highest_price":86.0},"title":"Dr. Dog with Saint Rich","announce_date":"2013-09-24T17:42:12","score":0.47464,"date_tbd":false,"type":"concert","datetime_local":"2014-03-03T21:00:00","visible_until_utc":"2014-03-04T09:00:00","time_tbd":false,"taxonomies":[{"parent_id":null,"id":2000000,"name":"concert"}],"performers":[{"name":"Dr. Dog","short_name":"Dr. Dog","url":"http://seatgeek.com/dr-dog-tickets","type":"band","image":"http://cdn.chairnerd.com/images/performers-landscape/dr-dog-5d6144/640/huge.jpg","primary":true,"home_venue_id":null,"slug":"dr-dog","score":0.52272,"images":{"huge":"http://cdn.chairnerd.com/images/performers-landscape/dr-dog-5d6144/640/huge.jpg","medium":"http://cdn.chairnerd.com/images/performers/640/dr-dog-f8a49b/medium.jpg","large":"http://cdn.chairnerd.com/images/performers/640/dr-dog-b47029/large.jpg","small":"http://cdn.chairnerd.com/images/performers/640/dr-dog-a0a3c9/small.jpg"},"id":640},{"name":"Saint Rich","short_name":"Saint Rich","url":"http://seatgeek.com/saint-rich-tickets","type":"band","image":null,"home_venue_id":null,"slug":"saint-rich","score":0.42852,"images":{},"id":252348}],"url":"http://seatgeek.com/dr-dog-with-saint-rich-tickets/portland-oregon-crystal-ballroom-1-2014-03-03-9-pm/concert/1806845/","created_at":"2013-09-24T17:42:12","venue":{"city":"Portland","name":"Crystal Ballroom","extended_address":"Portland, OR 97209","url":"http://seatgeek.com/venues/crystal-ballroom-1/tickets/","country":"US","display_location":"Portland, OR","links":[],"slug":"crystal-ballroom-1","state":"OR","score":0.54237,"postal_code":"97209","location":{"lat":45.5229,"lon":-122.685},"address":"1332 W. Burnside","timezone":"America/Los_Angeles","id":756},"short_title":"Dr. Dog with Saint Rich","datetime_utc":"2014-03-04T05:00:00","general_admission":true,"datetime_tbd":false},{"links":[],"id":1809714,"stats":{"listing_count":5,"average_price":85,"lowest_price":78,"highest_price":90},"title":"Dr. Dog","announce_date":"2013-09-26T17:37:31","score":0.50578,"date_tbd":false,"type":"concert","datetime_local":"2014-03-04T19:00:00","visible_until_utc":"2014-03-05T07:00:00","time_tbd":false,"taxonomies":[{"parent_id":null,"id":2000000,"name":"concert"}],"performers":[{"name":"Dr. Dog","short_name":"Dr. Dog","url":"http://seatgeek.com/dr-dog-tickets","type":"band","image":"http://cdn.chairnerd.com/images/performers-landscape/dr-dog-5d6144/640/huge.jpg","primary":true,"home_venue_id":null,"slug":"dr-dog","score":0.52272,"images":{"huge":"http://cdn.chairnerd.com/images/performers-landscape/dr-dog-5d6144/640/huge.jpg","medium":"http://cdn.chairnerd.com/images/performers/640/dr-dog-f8a49b/medium.jpg","large":"http://cdn.chairnerd.com/images/performers/640/dr-dog-b47029/large.jpg","small":"http://cdn.chairnerd.com/images/performers/640/dr-dog-a0a3c9/small.jpg"},"id":640}],"url":"http://seatgeek.com/dr-dog-tickets/vancouver-venue-2014-03-04-7-pm/concert/1809714/","created_at":"2013-09-26T17:37:31","venue":{"city":"Vancouver","name":"Venue","extended_address":"Vancouver, Canada","url":"http://seatgeek.com/venues/venue/tickets/","country":"Canada","display_location":"Vancouver, Canada","links":[],"slug":"venue","state":"BC","score":0.46714,"postal_code":"V6Z 1K7","location":{"lat":49.2805,"lon":-123.121},"address":"881 Granville Street","timezone":"America/Vancouver","id":1393},"short_title":"Dr. Dog","datetime_utc":"2014-03-05T03:00:00","general_admission":true,"datetime_tbd":false},{"links":[],"id":1809840,"stats":{"listing_count":7,"average_price":178.0,"lowest_price":71.0,"highest_price":182.0},"title":"Dr. Dog","announce_date":"2013-09-26T17:37:45","score":0.4781,"date_tbd":false,"type":"concert","datetime_local":"2014-03-05T19:00:00","visible_until_utc":"2014-03-06T07:00:00","time_tbd":false,"taxonomies":[{"parent_id":null,"id":2000000,"name":"concert"}],"performers":[{"name":"Dr. Dog","short_name":"Dr. Dog","url":"http://seatgeek.com/dr-dog-tickets","type":"band","image":"http://cdn.chairnerd.com/images/performers-landscape/dr-dog-5d6144/640/huge.jpg","primary":true,"home_venue_id":null,"slug":"dr-dog","score":0.52272,"images":{"huge":"http://cdn.chairnerd.com/images/performers-landscape/dr-dog-5d6144/640/huge.jpg","medium":"http://cdn.chairnerd.com/images/performers/640/dr-dog-f8a49b/medium.jpg","large":"http://cdn.chairnerd.com/images/performers/640/dr-dog-b47029/large.jpg","small":"http://cdn.chairnerd.com/images/performers/640/dr-dog-a0a3c9/small.jpg"},"id":640}],"url":"http://seatgeek.com/dr-dog-tickets/seattle-washington-neptune-theatre-2014-03-05-7-pm/concert/1809840/","created_at":"2013-09-26T17:37:45","venue":{"city":"Seattle","name":"Neptune Theatre","extended_address":"Seattle, WA 98105","url":"http://seatgeek.com/venues/neptune-theatre/tickets/","country":"US","display_location":"Seattle, WA","links":[],"slug":"neptune-theatre","state":"WA","score":0.48695,"postal_code":"98105","location":{"lat":47.6613,"lon":-122.314},"address":"1303 Northeast 45th Street","timezone":"America/Los_Angeles","id":5805},"short_title":"Dr. Dog","datetime_utc":"2014-03-06T03:00:00","general_admission":true,"datetime_tbd":false},{"links":[],"id":1809569,"stats":{"listing_count":12,"average_price":95.5,"lowest_price":52.0,"highest_price":182.0},"title":"Dr. Dog","announce_date":"2013-09-26T17:36:43","score":0.50996,"date_tbd":false,"type":"concert","datetime_local":"2014-03-07T19:00:00","visible_until_utc":"2014-03-08T06:00:00","time_tbd":false,"taxonomies":[{"parent_id":null,"id":2000000,"name":"concert"}],"performers":[{"name":"Dr. Dog","short_name":"Dr. Dog","url":"http://seatgeek.com/dr-dog-tickets","type":"band","image":"http://cdn.chairnerd.com/images/performers-landscape/dr-dog-5d6144/640/huge.jpg","primary":true,"home_venue_id":null,"slug":"dr-dog","score":0.52272,"images":{"huge":"http://cdn.chairnerd.com/images/performers-landscape/dr-dog-5d6144/640/huge.jpg","medium":"http://cdn.chairnerd.com/images/performers/640/dr-dog-f8a49b/medium.jpg","large":"http://cdn.chairnerd.com/images/performers/640/dr-dog-b47029/large.jpg","small":"http://cdn.chairnerd.com/images/performers/640/dr-dog-a0a3c9/small.jpg"},"id":640}],"url":"http://seatgeek.com/dr-dog-tickets/salt-lake-city-utah-the-complex-2014-03-07-7-pm/concert/1809569/","created_at":"2013-09-26T17:36:43","venue":{"city":"Salt Lake City","name":"The Complex","extended_address":"Salt Lake City, UT 84101","url":"http://seatgeek.com/venues/the-complex/tickets/","country":"US","display_location":"Salt Lake City, UT","links":[],"slug":"the-complex","state":"UT","score":0.51315,"postal_code":"84101","location":{"lat":40.7557,"lon":-111.844},"address":"536 West 100 South","timezone":"America/Denver","id":3605},"short_title":"Dr. Dog","datetime_utc":"2014-03-08T02:00:00","general_admission":true,"datetime_tbd":false},{"links":[],"id":1809561,"stats":{"listing_count":15,"average_price":104,"lowest_price":54,"highest_price":159},"title":"Dr. Dog","announce_date":"2013-09-26T17:36:26","score":0.48768,"date_tbd":false,"type":"concert","datetime_local":"2014-03-08T21:00:00","visible_until_utc":"2014-03-09T08:00:00","time_tbd":false,"taxonomies":[{"parent_id":null,"id":2000000,"name":"concert"}],"performers":[{"name":"Dr. Dog","short_name":"Dr. Dog","url":"http://seatgeek.com/dr-dog-tickets","type":"band","image":"http://cdn.chairnerd.com/images/performers-landscape/dr-dog-5d6144/640/huge.jpg","primary":true,"home_venue_id":null,"slug":"dr-dog","score":0.52272,"images":{"huge":"http://cdn.chairnerd.com/images/performers-landscape/dr-dog-5d6144/640/huge.jpg","medium":"http://cdn.chairnerd.com/images/performers/640/dr-dog-f8a49b/medium.jpg","large":"http://cdn.chairnerd.com/images/performers/640/dr-dog-b47029/large.jpg","small":"http://cdn.chairnerd.com/images/performers/640/dr-dog-a0a3c9/small.jpg"},"id":640}],"url":"http://seatgeek.com/dr-dog-tickets/boulder-colorado-boulder-theater-2014-03-08-9-pm/concert/1809561/","created_at":"2013-09-26T17:36:26","venue":{"city":"Boulder","name":"Boulder Theater","extended_address":"Boulder, CO 80302","url":"http://seatgeek.com/venues/boulder-theater/tickets/","country":"US","display_location":"Boulder, CO","links":[],"slug":"boulder-theater","state":"CO","score":0.49243,"postal_code":"80302","location":{"lat":40.1691,"lon":-105.058},"address":"2032 14th Street","timezone":"America/Denver","id":1031},"short_title":"Dr. Dog","datetime_utc":"2014-03-09T04:00:00","general_admission":true,"datetime_tbd":false},{"links":[],"id":1809623,"stats":{"listing_count":14,"average_price":117.71,"lowest_price":79,"highest_price":182},"title":"Dr. Dog","announce_date":"2013-09-26T17:37:21","score":0.50637,"date_tbd":false,"type":"concert","datetime_local":"2014-03-10T20:00:00","visible_until_utc":"2014-03-11T05:00:00","time_tbd":false,"taxonomies":[{"parent_id":null,"id":2000000,"name":"concert"}],"performers":[{"name":"Dr. Dog","short_name":"Dr. Dog","url":"http://seatgeek.com/dr-dog-tickets","type":"band","image":"http://cdn.chairnerd.com/images/performers-landscape/dr-dog-5d6144/640/huge.jpg","primary":true,"home_venue_id":null,"slug":"dr-dog","score":0.52272,"images":{"huge":"http://cdn.chairnerd.com/images/performers-landscape/dr-dog-5d6144/640/huge.jpg","medium":"http://cdn.chairnerd.com/images/performers/640/dr-dog-f8a49b/medium.jpg","large":"http://cdn.chairnerd.com/images/performers/640/dr-dog-b47029/large.jpg","small":"http://cdn.chairnerd.com/images/performers/640/dr-dog-a0a3c9/small.jpg"},"id":640}],"url":"http://seatgeek.com/dr-dog-tickets/lawrence-kansas-liberty-hall-2014-03-10-8-pm/concert/1809623/","created_at":"2013-09-26T17:37:21","venue":{"city":"Lawrence","name":"Liberty Hall","extended_address":"Lawrence, KS 66044","url":"http://seatgeek.com/venues/liberty-hall/tickets/","country":"US","display_location":"Lawrence, KS","links":[],"slug":"liberty-hall","state":"KS","score":0.47565,"postal_code":"66044","location":{"lat":38.9721,"lon":-95.2359},"address":"644 Massachusettes","timezone":"America/Chicago","id":789},"short_title":"Dr. Dog","datetime_utc":"2014-03-11T01:00:00","datetime_tbd":false},{"links":[],"id":1809595,"stats":{"listing_count":0,"average_price":null,"lowest_price":null,"highest_price":null},"title":"Dr. Dog","announce_date":"2013-09-26T17:37:16","score":0.50658,"date_tbd":false,"type":"concert","datetime_local":"2014-03-11T19:00:00","visible_until_utc":"2014-03-12T04:00:00","time_tbd":false,"taxonomies":[{"parent_id":null,"id":2000000,"name":"concert"}],"performers":[{"name":"Dr. Dog","short_name":"Dr. Dog","url":"http://seatgeek.com/dr-dog-tickets","type":"band","image":"http://cdn.chairnerd.com/images/performers-landscape/dr-dog-5d6144/640/huge.jpg","primary":true,"home_venue_id":null,"slug":"dr-dog","score":0.52272,"images":{"huge":"http://cdn.chairnerd.com/images/performers-landscape/dr-dog-5d6144/640/huge.jpg","medium":"http://cdn.chairnerd.com/images/performers/640/dr-dog-f8a49b/medium.jpg","large":"http://cdn.chairnerd.com/images/performers/640/dr-dog-b47029/large.jpg","small":"http://cdn.chairnerd.com/images/performers/640/dr-dog-a0a3c9/small.jpg"},"id":640}],"url":"http://seatgeek.com/dr-dog-tickets/omaha-nebraska-slowdown-2014-03-11-7-pm/concert/1809595/","created_at":"2013-09-26T17:37:16","venue":{"city":"Omaha","name":"Slowdown","extended_address":"Omaha, NE 68102","url":"http://seatgeek.com/venues/slowdown/tickets/","country":"US","display_location":"Omaha, NE","links":[],"slug":"slowdown","state":"NE","score":0.47838,"postal_code":"68102","location":{"lat":41.2662,"lon":-95.9345},"address":"729 N. 14th Street","timezone":"America/Chicago","id":942},"short_title":"Dr. Dog","datetime_utc":"2014-03-12T00:00:00","general_admission":true,"datetime_tbd":false},{"links":[],"id":1809617,"stats":{"listing_count":16,"average_price":94.5,"lowest_price":87,"highest_price":182},"title":"Dr. Dog","announce_date":"2013-09-26T17:37:20","score":0.50024,"date_tbd":false,"type":"concert","datetime_local":"2014-03-14T19:00:00","visible_until_utc":"2014-03-15T03:00:00","time_tbd":false,"taxonomies":[{"parent_id":null,"id":2000000,"name":"concert"}],"performers":[{"name":"Dr. Dog","short_name":"Dr. Dog","url":"http://seatgeek.com/dr-dog-tickets","type":"band","image":"http://cdn.chairnerd.com/images/performers-landscape/dr-dog-5d6144/640/huge.jpg","primary":true,"home_venue_id":null,"slug":"dr-dog","score":0.52272,"images":{"huge":"http://cdn.chairnerd.com/images/performers-landscape/dr-dog-5d6144/640/huge.jpg","medium":"http://cdn.chairnerd.com/images/performers/640/dr-dog-f8a49b/medium.jpg","large":"http://cdn.chairnerd.com/images/performers/640/dr-dog-b47029/large.jpg","small":"http://cdn.chairnerd.com/images/performers/640/dr-dog-a0a3c9/small.jpg"},"id":640}],"url":"http://seatgeek.com/dr-dog-tickets/washington-district-of-columbia-9-30-club-2014-03-14-7-pm/concert/1809617/","created_at":"2013-09-26T17:37:20","venue":{"city":"Washington","name":"9:30 Club","extended_address":"Washington, DC 20001","url":"http://seatgeek.com/venues/9-30-club/tickets/","country":"US","display_location":"Washington, DC","links":[],"slug":"9-30-club","state":"DC","score":0.55512,"postal_code":"20001","location":{"lat":38.9178,"lon":-77.0236},"address":"815 V St. NW","timezone":"America/New_York","id":538},"short_title":"Dr. Dog","datetime_utc":"2014-03-14T23:00:00","general_admission":true,"datetime_tbd":false},{"links":[],"id":2011061,"stats":{"listing_count":null,"average_price":null,"lowest_price":null,"highest_price":null},"title":"Dr. Dog","announce_date":"2014-02-18T16:27:38","score":0.51658,"date_tbd":false,"type":"concert","datetime_local":"2014-03-15T20:00:00","visible_until_utc":"2014-03-16T04:00:00","time_tbd":false,"taxonomies":[{"parent_id":null,"id":2000000,"name":"concert"}],"performers":[{"name":"Dr. Dog","short_name":"Dr. Dog","url":"http://seatgeek.com/dr-dog-tickets","type":"band","image":"http://cdn.chairnerd.com/images/performers-landscape/dr-dog-5d6144/640/huge.jpg","primary":true,"home_venue_id":null,"slug":"dr-dog","score":0.52272,"images":{"huge":"http://cdn.chairnerd.com/images/performers-landscape/dr-dog-5d6144/640/huge.jpg","medium":"http://cdn.chairnerd.com/images/performers/640/dr-dog-f8a49b/medium.jpg","large":"http://cdn.chairnerd.com/images/performers/640/dr-dog-b47029/large.jpg","small":"http://cdn.chairnerd.com/images/performers/640/dr-dog-a0a3c9/small.jpg"},"id":640}],"url":"http://seatgeek.com/dr-dog-tickets/washington-district-of-columbia-9-30-club-2014-03-15-8-pm/concert/2011061/","created_at":"2014-02-18T16:27:38","venue":{"city":"Washington","name":"9:30 Club","extended_address":"Washington, DC 20001","url":"http://seatgeek.com/venues/9-30-club/tickets/","country":"US","display_location":"Washington, DC","links":[],"slug":"9-30-club","state":"DC","score":0.55512,"postal_code":"20001","location":{"lat":38.9178,"lon":-77.0236},"address":"815 V St. NW","timezone":"America/New_York","id":538},"short_title":"Dr. Dog","datetime_utc":"2014-03-16T00:00:00","general_admission":true,"datetime_tbd":false},{"links":[],"id":2012744,"stats":{"listing_count":null,"average_price":null,"lowest_price":null,"highest_price":null},"title":"Dr. Dog with The Districts","announce_date":"2014-02-19T00:00:00","score":0.48827,"date_tbd":false,"type":"concert","datetime_local":"2014-06-05T19:00:00","visible_until_utc":"2014-06-06T04:00:00","time_tbd":false,"taxonomies":[{"parent_id":null,"id":2000000,"name":"concert"}],"performers":[{"name":"Dr. Dog","short_name":"Dr. Dog","url":"http://seatgeek.com/dr-dog-tickets","type":"band","image":"http://cdn.chairnerd.com/images/performers-landscape/dr-dog-5d6144/640/huge.jpg","primary":true,"home_venue_id":null,"slug":"dr-dog","score":0.52272,"images":{"huge":"http://cdn.chairnerd.com/images/performers-landscape/dr-dog-5d6144/640/huge.jpg","medium":"http://cdn.chairnerd.com/images/performers/640/dr-dog-f8a49b/medium.jpg","large":"http://cdn.chairnerd.com/images/performers/640/dr-dog-b47029/large.jpg","small":"http://cdn.chairnerd.com/images/performers/640/dr-dog-a0a3c9/small.jpg"},"id":640},{"name":"The Districts","short_name":"The Districts","url":"http://seatgeek.com/the-districts-tickets","type":"band","image":null,"home_venue_id":null,"slug":"the-districts","score":0.35735,"images":{},"id":85587}],"url":"http://seatgeek.com/dr-dog-with-the-districts-tickets/tulsa-oklahoma-cains-ballroom-2014-06-05-7-pm/concert/2012744/","created_at":"2014-02-19T00:00:00","venue":{"city":"Tulsa","name":"Cains Ballroom","extended_address":"Tulsa, OK 74103","url":"http://seatgeek.com/venues/cains-ballroom/tickets/","country":"US","display_location":"Tulsa, OK","links":[],"slug":"cains-ballroom","state":"OK","score":0.50125,"postal_code":"74103","location":{"lat":36.1605,"lon":-95.9948},"address":"423 North Main Street","timezone":"America/Chicago","id":421},"short_title":"Dr. Dog with The Districts","datetime_utc":"2014-06-06T00:00:00","general_admission":true,"datetime_tbd":false},{"links":[],"id":2012537,"stats":{"listing_count":null,"average_price":null,"lowest_price":null,"highest_price":null},"title":"Dr. Dog with The Districts","announce_date":"2014-02-19T00:00:00","score":0.4822,"date_tbd":false,"type":"concert","datetime_local":"2014-06-07T21:00:00","visible_until_utc":"2014-06-08T06:00:00","time_tbd":false,"taxonomies":[{"parent_id":null,"id":2000000,"name":"concert"}],"performers":[{"name":"Dr. Dog","short_name":"Dr. Dog","url":"http://seatgeek.com/dr-dog-tickets","type":"band","image":"http://cdn.chairnerd.com/images/performers-landscape/dr-dog-5d6144/640/huge.jpg","primary":true,"home_venue_id":null,"slug":"dr-dog","score":0.52272,"images":{"huge":"http://cdn.chairnerd.com/images/performers-landscape/dr-dog-5d6144/640/huge.jpg","medium":"http://cdn.chairnerd.com/images/performers/640/dr-dog-f8a49b/medium.jpg","large":"http://cdn.chairnerd.com/images/performers/640/dr-dog-b47029/large.jpg","small":"http://cdn.chairnerd.com/images/performers/640/dr-dog-a0a3c9/small.jpg"},"id":640},{"name":"The Districts","short_name":"The Districts","url":"http://seatgeek.com/the-districts-tickets","type":"band","image":null,"home_venue_id":null,"slug":"the-districts","score":0.35735,"images":{},"id":85587}],"url":"http://seatgeek.com/dr-dog-with-the-districts-tickets/columbia-missouri-the-blue-note-2014-06-07-9-pm/concert/2012537/","created_at":"2014-02-19T00:00:00","venue":{"city":"Columbia","name":"The Blue Note","extended_address":"Columbia, MO 65201","url":"http://seatgeek.com/venues/the-blue-note/tickets/","country":"US","display_location":"Columbia, MO","links":[],"slug":"the-blue-note","state":"MO","score":0.44034,"postal_code":"65201","location":{"lat":38.9521,"lon":-92.3275},"address":"17 N 9th St","timezone":"America/Chicago","id":943},"short_title":"Dr. Dog with The Districts","datetime_utc":"2014-06-08T02:00:00","general_admission":true,"datetime_tbd":false},{"links":[],"id":1995715,"stats":{"listing_count":0,"average_price":null,"lowest_price":null,"highest_price":null},"title":"Dr. Dog with The Districts","announce_date":"2014-02-07T16:46:38","score":0.48128,"date_tbd":false,"type":"concert","datetime_local":"2014-06-08T20:00:00","visible_until_utc":"2014-06-09T04:00:00","time_tbd":false,"taxonomies":[{"parent_id":null,"id":2000000,"name":"concert"}],"performers":[{"name":"Dr. Dog","short_name":"Dr. Dog","url":"http://seatgeek.com/dr-dog-tickets","type":"band","image":"http://cdn.chairnerd.com/images/performers-landscape/dr-dog-5d6144/640/huge.jpg","primary":true,"home_venue_id":null,"slug":"dr-dog","score":0.52272,"images":{"huge":"http://cdn.chairnerd.com/images/performers-landscape/dr-dog-5d6144/640/huge.jpg","medium":"http://cdn.chairnerd.com/images/performers/640/dr-dog-f8a49b/medium.jpg","large":"http://cdn.chairnerd.com/images/performers/640/dr-dog-b47029/large.jpg","small":"http://cdn.chairnerd.com/images/performers/640/dr-dog-a0a3c9/small.jpg"},"id":640},{"name":"The Districts","short_name":"The Districts","url":"http://seatgeek.com/the-districts-tickets","type":"band","image":null,"home_venue_id":null,"slug":"the-districts","score":0.35735,"images":{},"id":85587}],"url":"http://seatgeek.com/dr-dog-with-the-districts-tickets/indianapolis-indiana-the-vogue-3-2014-06-08-8-pm/concert/1995715/","created_at":"2014-02-07T16:46:38","venue":{"city":"Indianapolis","name":"The Vogue","extended_address":"Indianapolis, IN 46220","url":"http://seatgeek.com/venues/the-vogue-3/tickets/","country":"US","display_location":"Indianapolis, IN","links":[],"slug":"the-vogue-3","state":"IN","score":0.42475,"postal_code":"46220","location":{"lat":39.87,"lon":-86.15},"address":"6259 N. College Ave.","timezone":"America/New_York","id":8821},"short_title":"Dr. Dog with The Districts","datetime_utc":"2014-06-09T00:00:00","general_admission":true,"datetime_tbd":false},{"links":[],"id":2012456,"stats":{"listing_count":15,"average_price":69.0,"lowest_price":55.0,"highest_price":229.0},"title":"Dr. Dog with The Districts","announce_date":"2014-02-19T00:00:00","score":0.49808,"date_tbd":false,"type":"concert","datetime_local":"2014-06-10T19:00:00","visible_until_utc":"2014-06-11T03:00:00","time_tbd":false,"taxonomies":[{"parent_id":null,"id":2000000,"name":"concert"}],"performers":[{"name":"Dr. Dog","short_name":"Dr. Dog","url":"http://seatgeek.com/dr-dog-tickets","type":"band","image":"http://cdn.chairnerd.com/images/performers-landscape/dr-dog-5d6144/640/huge.jpg","primary":true,"home_venue_id":null,"slug":"dr-dog","score":0.52272,"images":{"huge":"http://cdn.chairnerd.com/images/performers-landscape/dr-dog-5d6144/640/huge.jpg","medium":"http://cdn.chairnerd.com/images/performers/640/dr-dog-f8a49b/medium.jpg","large":"http://cdn.chairnerd.com/images/performers/640/dr-dog-b47029/large.jpg","small":"http://cdn.chairnerd.com/images/performers/640/dr-dog-a0a3c9/small.jpg"},"id":640},{"name":"The Districts","short_name":"The Districts","url":"http://seatgeek.com/the-districts-tickets","type":"band","image":null,"home_venue_id":null,"slug":"the-districts","score":0.35735,"images":{},"id":85587}],"url":"http://seatgeek.com/dr-dog-with-the-districts-tickets/pittsburgh-pennsylvania-stage-ae-2014-06-10-7-pm/concert/2012456/","created_at":"2014-02-19T00:00:00","venue":{"city":"Pittsburgh","name":"Stage AE","extended_address":"Pittsburgh, PA 15212","url":"http://seatgeek.com/venues/stage-ae/tickets/","country":"US","display_location":"Pittsburgh, PA","links":[],"slug":"stage-ae","state":"PA","score":0.55152,"postal_code":"15212","location":{"lat":40.4457,"lon":-80.0125},"address":"400 North Shore Drive","timezone":"America/New_York","id":3386},"short_title":"Dr. Dog with The Districts","datetime_utc":"2014-06-10T23:00:00","general_admission":true,"datetime_tbd":false},{"links":[],"id":2012529,"stats":{"listing_count":null,"average_price":null,"lowest_price":null,"highest_price":null},"title":"Dr. Dog","announce_date":"2014-02-19T00:00:00","score":0.50581,"date_tbd":false,"type":"concert","datetime_local":"2014-06-11T21:00:00","visible_until_utc":"2014-06-12T05:00:00","time_tbd":false,"taxonomies":[{"parent_id":null,"id":2000000,"name":"concert"}],"performers":[{"name":"Dr. Dog","short_name":"Dr. Dog","url":"http://seatgeek.com/dr-dog-tickets","type":"band","image":"http://cdn.chairnerd.com/images/performers-landscape/dr-dog-5d6144/640/huge.jpg","primary":true,"home_venue_id":null,"slug":"dr-dog","score":0.52272,"images":{"huge":"http://cdn.chairnerd.com/images/performers-landscape/dr-dog-5d6144/640/huge.jpg","medium":"http://cdn.chairnerd.com/images/performers/640/dr-dog-f8a49b/medium.jpg","large":"http://cdn.chairnerd.com/images/performers/640/dr-dog-b47029/large.jpg","small":"http://cdn.chairnerd.com/images/performers/640/dr-dog-a0a3c9/small.jpg"},"id":640}],"url":"http://seatgeek.com/dr-dog-tickets/carrboro-north-carolina-cat-s-cradle-2014-06-11-9-pm/concert/2012529/","created_at":"2014-02-19T00:00:00","venue":{"city":"Carrboro","name":"Cat's Cradle","extended_address":"Carrboro, NC 27510","url":"http://seatgeek.com/venues/cat-s-cradle/tickets/","country":"US","display_location":"Carrboro, NC","links":[],"slug":"cat-s-cradle","state":"NC","score":0.4676,"postal_code":"27510","location":{"lat":35.9108,"lon":-79.0685},"address":"300 East Main Street","timezone":"America/New_York","id":1076},"short_title":"Dr. Dog","datetime_utc":"2014-06-12T01:00:00","general_admission":true,"datetime_tbd":false}]}